{
	"l10n_heading_rootca": {
		"de": "Ausstellende CA"
	},
	"l10n_text_rootcaexpl1": {
		"de": "Dies ist das Zertifikat, welches wird verwenden, um die CSRs zu unterzeichnen, die wir erhalten."
	},
	"l10n_text_rootcaexpl2": {
		"de": "Um das Zertifikat im Browser zu betrachten, dr\u00fccken Sie"
	},
	"l10n_text_here": {
		"de": "hier"
	},
	"l10n_link_direct": {
		"de": "Direkter Link"
	},
	"l10n_text_rootcaexpl3": {
		"de": "zum Zertifikat (Installation)."
	},
	"l10n_text_downldirect": {
		"de": "Falls Sie es direkt herunterladen wollen:"
	},
	"l10n_button_download": {
		"de": "Download"
	},
	"l10n_text_crlexpl1": {
		"de": "Die CRL (Zertifikatswiderrufsliste) ist eine Liste aller widerrufenen (ung\u00fcltigen) Zertifikate, ver\u00f6ffentlicht von dieser CA."
	},
	"l10n_text_crlexpl2": {
		"de": "Zeige die CRL im Browser:"
	},
	"l10n_text_crldili": {
		"de": "Direkter Link zur CRL (Installation):"
	},
	"l10n_heading_cadump": {
		"de": "CA-Zertifikat:"
	},
	"l10n_heading_crldump": {
		"de": "CRL:"
	}
}
